loggerFactory/__init__.py
loggerFactory/_version.py
loggerFactory/logfilter.py
loggerFactory/logger.py
loggerFactory/rand_str.py
loggerFactory/__pycache__/__init__.cpython-38.pyc
loggerFactory/__pycache__/_version.cpython-38.pyc
loggerFactory/__pycache__/logfilter.cpython-38.pyc
loggerFactory/__pycache__/logger.cpython-38.pyc
loggerFactory/__pycache__/rand_str.cpython-38.pyc
loggerFactory/docs/__init__.py
loggerFactory-0.0.6.dist-info/AUTHORS.rst
loggerFactory-0.0.6.dist-info/LICENSE.txt
loggerFactory-0.0.6.dist-info/METADATA
loggerFactory-0.0.6.dist-info/WHEEL
loggerFactory-0.0.6.dist-info/top_level.txt
loggerFactory-0.0.6.dist-info/RECORD
